phone_format/__init__.py
phone_format/format_phone.py
phone_format-0.1.6.dist-info/METADATA
phone_format-0.1.6.dist-info/WHEEL
phone_format-0.1.6.dist-info/RECORD
