Metadata-Version: 2.1
Name: phone_format
Version: 0.1.6
Summary: This project includes different phone formatting
License: MIT
Author: Jean Eric TUYISHIMIRE
Author-email: 81187224+tjeaneric@users.noreply.github.com
Requires-Python: >=3.8,<4.0
Classifier: License :: OSI Approved :: MIT License
Classifier: Programming Language :: Python :: 3
Classifier: Programming Language :: Python :: 3.8
Classifier: Programming Language :: Python :: 3.9
Classifier: Programming Language :: Python :: 3.10
Classifier: Programming Language :: Python :: 3.11
Classifier: Programming Language :: Python :: 3.12
